<?xml version="1.0" encoding="utf-8"?>
<TextureAtlas imagePath="wahoo-sunny.png">
	<!-- Created with Adobe Animate version 24.0.12.3 -->
	<!-- http://www.adobe.com/products/animate.html -->
	<SubTexture name="down0000" x="5" y="5" width="504" height="443" frameX="0" frameY="-11" frameWidth="508" frameHeight="456"/>
	<SubTexture name="down0001" x="5" y="5" width="504" height="443" frameX="0" frameY="-11" frameWidth="508" frameHeight="456"/>
	<SubTexture name="down0002" x="514" y="5" width="494" height="456" frameX="-14" frameY="0" frameWidth="508" frameHeight="456"/>
	<SubTexture name="down0003" x="514" y="5" width="494" height="456" frameX="-14" frameY="0" frameWidth="508" frameHeight="456"/>
	<SubTexture name="down0004" x="514" y="5" width="494" height="456" frameX="-14" frameY="0" frameWidth="508" frameHeight="456"/>
	<SubTexture name="down0005" x="514" y="5" width="494" height="456" frameX="-14" frameY="0" frameWidth="508" frameHeight="456"/>
	<SubTexture name="down0006" x="514" y="5" width="494" height="456" frameX="-14" frameY="0" frameWidth="508" frameHeight="456"/>
	<SubTexture name="down0007" x="514" y="5" width="494" height="456" frameX="-14" frameY="0" frameWidth="508" frameHeight="456"/>
	<SubTexture name="down0008" x="514" y="5" width="494" height="456" frameX="-14" frameY="0" frameWidth="508" frameHeight="456"/>
	<SubTexture name="down0009" x="514" y="5" width="494" height="456" frameX="-14" frameY="0" frameWidth="508" frameHeight="456"/>
	<SubTexture name="down0010" x="514" y="5" width="494" height="456" frameX="-14" frameY="0" frameWidth="508" frameHeight="456"/>
	<SubTexture name="down0011" x="514" y="5" width="494" height="456" frameX="-14" frameY="0" frameWidth="508" frameHeight="456"/>
	<SubTexture name="down0012" x="514" y="5" width="494" height="456" frameX="-14" frameY="0" frameWidth="508" frameHeight="456"/>
	<SubTexture name="down0013" x="514" y="5" width="494" height="456" frameX="-14" frameY="0" frameWidth="508" frameHeight="456"/>
	<SubTexture name="idle0000" x="1013" y="5" width="379" height="459" frameX="0" frameY="-5" frameWidth="381" frameHeight="465"/>
	<SubTexture name="idle0001" x="1013" y="5" width="379" height="459" frameX="0" frameY="-5" frameWidth="381" frameHeight="465"/>
	<SubTexture name="idle0002" x="1397" y="5" width="380" height="461" frameX="-1" frameY="-3" frameWidth="381" frameHeight="465"/>
	<SubTexture name="idle0003" x="1397" y="5" width="380" height="461" frameX="-1" frameY="-3" frameWidth="381" frameHeight="465"/>
	<SubTexture name="idle0004" x="5" y="471" width="373" height="464" frameX="-4" frameY="0" frameWidth="381" frameHeight="465"/>
	<SubTexture name="idle0005" x="5" y="471" width="373" height="464" frameX="-4" frameY="0" frameWidth="381" frameHeight="465"/>
	<SubTexture name="idle0006" x="383" y="471" width="369" height="465" frameX="-5" frameY="0" frameWidth="381" frameHeight="465"/>
	<SubTexture name="idle0007" x="383" y="471" width="369" height="465" frameX="-5" frameY="0" frameWidth="381" frameHeight="465"/>
	<SubTexture name="idle0008" x="383" y="471" width="369" height="465" frameX="-5" frameY="0" frameWidth="381" frameHeight="465"/>
	<SubTexture name="idle0009" x="383" y="471" width="369" height="465" frameX="-5" frameY="0" frameWidth="381" frameHeight="465"/>
	<SubTexture name="idle0010" x="383" y="471" width="369" height="465" frameX="-5" frameY="0" frameWidth="381" frameHeight="465"/>
	<SubTexture name="idle0011" x="383" y="471" width="369" height="465" frameX="-5" frameY="0" frameWidth="381" frameHeight="465"/>
	<SubTexture name="idle0012" x="383" y="471" width="369" height="465" frameX="-5" frameY="0" frameWidth="381" frameHeight="465"/>
	<SubTexture name="idle0013" x="383" y="471" width="369" height="465" frameX="-5" frameY="0" frameWidth="381" frameHeight="465"/>
	<SubTexture name="left0000" x="757" y="471" width="365" height="462" frameX="-16" frameY="-1" frameWidth="383" frameHeight="465"/>
	<SubTexture name="left0001" x="757" y="471" width="365" height="462" frameX="-16" frameY="-1" frameWidth="383" frameHeight="465"/>
	<SubTexture name="left0002" x="1127" y="471" width="383" height="465"/>
	<SubTexture name="left0003" x="1127" y="471" width="383" height="465"/>
	<SubTexture name="left0004" x="1127" y="471" width="383" height="465"/>
	<SubTexture name="left0005" x="1127" y="471" width="383" height="465"/>
	<SubTexture name="left0006" x="1127" y="471" width="383" height="465"/>
	<SubTexture name="left0007" x="1127" y="471" width="383" height="465"/>
	<SubTexture name="left0008" x="1127" y="471" width="383" height="465"/>
	<SubTexture name="left0009" x="1127" y="471" width="383" height="465"/>
	<SubTexture name="left0010" x="1127" y="471" width="383" height="465"/>
	<SubTexture name="left0011" x="1127" y="471" width="383" height="465"/>
	<SubTexture name="left0012" x="1127" y="471" width="383" height="465"/>
	<SubTexture name="left0013" x="1127" y="471" width="383" height="465"/>
	<SubTexture name="right0000" x="1515" y="471" width="491" height="465" frameX="0" frameY="0" frameWidth="503" frameHeight="465"/>
	<SubTexture name="right0001" x="1515" y="471" width="491" height="465" frameX="0" frameY="0" frameWidth="503" frameHeight="465"/>
	<SubTexture name="right0002" x="5" y="941" width="500" height="465" frameX="-3" frameY="0" frameWidth="503" frameHeight="465"/>
	<SubTexture name="right0003" x="5" y="941" width="500" height="465" frameX="-3" frameY="0" frameWidth="503" frameHeight="465"/>
	<SubTexture name="right0004" x="5" y="941" width="500" height="465" frameX="-3" frameY="0" frameWidth="503" frameHeight="465"/>
	<SubTexture name="right0005" x="5" y="941" width="500" height="465" frameX="-3" frameY="0" frameWidth="503" frameHeight="465"/>
	<SubTexture name="right0006" x="5" y="941" width="500" height="465" frameX="-3" frameY="0" frameWidth="503" frameHeight="465"/>
	<SubTexture name="right0007" x="5" y="941" width="500" height="465" frameX="-3" frameY="0" frameWidth="503" frameHeight="465"/>
	<SubTexture name="right0008" x="5" y="941" width="500" height="465" frameX="-3" frameY="0" frameWidth="503" frameHeight="465"/>
	<SubTexture name="right0009" x="5" y="941" width="500" height="465" frameX="-3" frameY="0" frameWidth="503" frameHeight="465"/>
	<SubTexture name="right0010" x="5" y="941" width="500" height="465" frameX="-3" frameY="0" frameWidth="503" frameHeight="465"/>
	<SubTexture name="right0011" x="5" y="941" width="500" height="465" frameX="-3" frameY="0" frameWidth="503" frameHeight="465"/>
	<SubTexture name="right0012" x="5" y="941" width="500" height="465" frameX="-3" frameY="0" frameWidth="503" frameHeight="465"/>
	<SubTexture name="right0013" x="5" y="941" width="500" height="465" frameX="-3" frameY="0" frameWidth="503" frameHeight="465"/>
	<SubTexture name="up0000" x="510" y="941" width="406" height="487" frameX="-1" frameY="0" frameWidth="409" frameHeight="487"/>
	<SubTexture name="up0001" x="510" y="941" width="406" height="487" frameX="-1" frameY="0" frameWidth="409" frameHeight="487"/>
	<SubTexture name="up0002" x="921" y="941" width="409" height="478" frameX="0" frameY="-10" frameWidth="409" frameHeight="487"/>
	<SubTexture name="up0003" x="921" y="941" width="409" height="478" frameX="0" frameY="-10" frameWidth="409" frameHeight="487"/>
	<SubTexture name="up0004" x="921" y="941" width="409" height="478" frameX="0" frameY="-10" frameWidth="409" frameHeight="487"/>
	<SubTexture name="up0005" x="921" y="941" width="409" height="478" frameX="0" frameY="-10" frameWidth="409" frameHeight="487"/>
	<SubTexture name="up0006" x="921" y="941" width="409" height="478" frameX="0" frameY="-10" frameWidth="409" frameHeight="487"/>
	<SubTexture name="up0007" x="921" y="941" width="409" height="478" frameX="0" frameY="-10" frameWidth="409" frameHeight="487"/>
	<SubTexture name="up0008" x="921" y="941" width="409" height="478" frameX="0" frameY="-10" frameWidth="409" frameHeight="487"/>
	<SubTexture name="up0009" x="921" y="941" width="409" height="478" frameX="0" frameY="-10" frameWidth="409" frameHeight="487"/>
	<SubTexture name="up0010" x="921" y="941" width="409" height="478" frameX="0" frameY="-10" frameWidth="409" frameHeight="487"/>
	<SubTexture name="up0011" x="921" y="941" width="409" height="478" frameX="0" frameY="-10" frameWidth="409" frameHeight="487"/>
	<SubTexture name="up0012" x="921" y="941" width="409" height="478" frameX="0" frameY="-10" frameWidth="409" frameHeight="487"/>
	<SubTexture name="up0013" x="921" y="941" width="409" height="478" frameX="0" frameY="-10" frameWidth="409" frameHeight="487"/>
</TextureAtlas>
